supy/__init__.py
supy/_check.py
supy/_env.py
supy/_load.py
supy/_misc.py
supy/_post.py
supy/_run.py
supy/_save.py
supy/_supy_driver.cpython-312-x86_64-linux-gnu.so
supy/_supy_driver_wrapper.py
supy/_supy_module.py
supy/_version.py
supy/_version_scm.py
supy/checker_rules_indiv.json
supy/checker_rules_joint.json
supy/code2file.json
supy/suews_sim.py
supy/supy_driver.py
supy/var2siteselect.json
supy/cmd/SUEWS.py
supy/cmd/__init__.py
supy/cmd/schema_cli.py
supy/cmd/table_converter.py
supy/cmd/to_yaml.py
supy/cmd/validate_config.py
supy/data_model/README.md
supy/data_model/__init__.py
supy/data_model/doc_utils.py
supy/data_model/core/__init__.py
supy/data_model/core/config.py
supy/data_model/core/human_activity.py
supy/data_model/core/hydro.py
supy/data_model/core/model.py
supy/data_model/core/ohm.py
supy/data_model/core/profile.py
supy/data_model/core/site.py
supy/data_model/core/state.py
supy/data_model/core/surface.py
supy/data_model/core/timezone_enum.py
supy/data_model/core/type.py
supy/data_model/schema/__init__.py
supy/data_model/schema/exporter.py
supy/data_model/schema/migration.py
supy/data_model/schema/publisher.py
supy/data_model/schema/registry.py
supy/data_model/schema/updater.py
supy/data_model/schema/version.py
supy/data_model/validation/__init__.py
supy/data_model/validation/core/__init__.py
supy/data_model/validation/core/controller.py
supy/data_model/validation/core/feedback.py
supy/data_model/validation/core/utils.py
supy/data_model/validation/core/yaml_helpers.py
supy/data_model/validation/pipeline/__init__.py
supy/data_model/validation/pipeline/orchestrator.py
supy/data_model/validation/pipeline/phase_a.py
supy/data_model/validation/pipeline/phase_b.py
supy/data_model/validation/pipeline/phase_c.py
supy/data_model/validation/pipeline/yaml_annotator.py
supy/ext_data/CRU_TS4.06_1991_2020.parquet
supy/ext_data/README.md
supy/sample_data/Kc_2012_data_60.txt
supy-2025.10.15.dist-info/METADATA
supy-2025.10.15.dist-info/WHEEL
supy-2025.10.15.dist-info/entry_points.txt
supy-2025.10.15.dist-info/RECORD
