Metadata-Version: 2.1
Name: supy
Version: 2025.10.15
Summary: The SUEWS model that speaks Python
Author-Email: Dr Ting Sun <ting.sun@ucl.ac.uk>
License: GPL-V3.0
Classifier: Programming Language :: Python :: 3 :: Only
Classifier: Programming Language :: Python :: 3.9
Classifier: Programming Language :: Python :: 3.10
Classifier: Programming Language :: Python :: 3.11
Classifier: Programming Language :: Python :: 3.12
Classifier: Programming Language :: Python :: 3.13
Classifier: Intended Audience :: Science/Research
Classifier: Intended Audience :: Education
Classifier: Operating System :: MacOS :: MacOS X
Classifier: Operating System :: Microsoft :: Windows
Classifier: Operating System :: POSIX :: Linux
Requires-Python: >=3.9
Requires-Dist: pandas
Requires-Dist: numpy>=2.0
Requires-Dist: scipy
Requires-Dist: xarray
Requires-Dist: dask
Requires-Dist: f90wrap==0.2.16
Requires-Dist: pydantic
Requires-Dist: f90nml
Requires-Dist: matplotlib
Requires-Dist: seaborn
Requires-Dist: chardet
Requires-Dist: click
Requires-Dist: pyarrow
Requires-Dist: atmosp
Requires-Dist: scikit-learn
Requires-Dist: lmfit
Requires-Dist: numdifftools
Requires-Dist: platypus-opt==1.0.4
Requires-Dist: cdsapi
Requires-Dist: tzfpy>=1.0.0
Requires-Dist: pytz
Requires-Dist: multiprocess
Requires-Dist: jsonschema
Requires-Dist: rich
Provides-Extra: tmy
Requires-Dist: pvlib; extra == "tmy"
Provides-Extra: dev
Requires-Dist: pytest; extra == "dev"
Requires-Dist: pytest-cov; extra == "dev"
Requires-Dist: ruff; extra == "dev"
Requires-Dist: fprettify; extra == "dev"
Requires-Dist: ipykernel; extra == "dev"
Requires-Dist: sphinx<8.2,>=4.0; extra == "dev"
Requires-Dist: sphinx-autobuild; extra == "dev"
Requires-Dist: sphinx-book-theme; extra == "dev"
Requires-Dist: nbsphinx; extra == "dev"
Requires-Dist: recommonmark; extra == "dev"
Requires-Dist: pybtex; extra == "dev"
Requires-Dist: sphinxcontrib.bibtex~=2.4; extra == "dev"
Requires-Dist: sphinx-panels; extra == "dev"
Requires-Dist: sphinx-design; extra == "dev"
Requires-Dist: sphinx-last-updated-by-git; extra == "dev"
Requires-Dist: sphinx-click; extra == "dev"
Requires-Dist: sphinx_comments; extra == "dev"
Requires-Dist: docutils<0.17,>=0.16; extra == "dev"
Requires-Dist: jinja2<3.1,>=3.0; extra == "dev"
